Pyubiomes/__init__.py
Pyubiomes/genconsts.py
Pyubiomes/searches.py
Pyubiomes/searches.so
Pyubiomes-0.1.2.dist-info/LICENSE.txt
Pyubiomes-0.1.2.dist-info/METADATA
Pyubiomes-0.1.2.dist-info/WHEEL
Pyubiomes-0.1.2.dist-info/top_level.txt
Pyubiomes-0.1.2.dist-info/RECORD
