Metadata-Version: 2.1
Name: Pyubiomes
Version: 0.1.2
Summary: a (probably bad wip) python wrapper for the C library Cubiomes
Home-page: https://github.com/4gboframram/Pyubiomes
Author: 4gboframram
Author-email: <zachawesomeness411@gmail.com>
License: UNKNOWN
Platform: UNKNOWN
